{"ip":0,"fr":60,"v":"5.1.20","assets":[],"layers":[{"ty":4,"nm":"Group 3","ip":0,"st":0,"ind":6,"hix":3,"ks":{"o":{"a":1,"k":[{"t":0,"s":[0],"e":[0],"i":{"x":[1],"y":[1]},"o":{"x":[0],"y":[0]}},{"t":359,"s":[0],"e":[100],"i":{"x":[1],"y":[1]},"o":{"x":[0],"y":[0]}},{"t":360,"s":[100],"e":[100],"i":{"x":[1],"y":[1]},"o":{"x":[0],"y":[0]}},{"t":479,"s":[100],"e":[0],"i":{"x":[1],"y":[1]},"o":{"x":[0],"y":[0]}},{"t":480}]},"or":{"a":0,"k":[0,0,0]},"a":{"a":0,"k":[124,88,0]},"p":{"s":true,"x":{"a":0,"k":250},"y":{"a":0,"k":250}},"rx":{"a":0,"k":0},"ry":{"a":0,"k":0},"rz":{"a":0,"k":0},"s":{"a":0,"k":[100,100,100]}},"shapes":[{"ty":"gr","nm":"Group 3 shape group","it":[{"ty":"sh","ks":{"a":0,"k":{"c":false,"v":[[12.5072,98.6643],[100.057,163.493],[235.285,12.5065]],"i":[[0,0],[0,0],[0,0]],"o":[[0,0],[0,0],[0,0]]}}},{"ty":"st","o":{"a":0,"k":100},"c":{"a":0,"k":[0.9490196078431372,0.5529411764705883,0.20784313725490197,1]},"lc":2,"lj":2,"ml":10,"w":{"a":0,"k":25},"d":[{"n":"d","v":{"a":0,"k":320},"nm":"0"},{"n":"g","v":{"a":0,"k":320},"nm":"1"},{"n":"o","v":{"a":1,"k":[{"t":0,"s":[320],"e":[320],"i":{"x":[1],"y":[1]},"o":{"x":[0],"y":[0]}},{"t":360,"s":[320],"e":[0],"i":{"x":[0.515],"y":[0.955]},"o":{"x":[0.455],"y":[0.03]}},{"t":480}]},"nm":"2"}]},{"ty":"fl","o":{"a":0,"k":0},"c":{"a":0,"k":[0,0,0,0]},"r":1},{"ty":"tr","o":{"a":0,"k":100},"a":{"a":0,"k":[0,0]},"s":{"a":0,"k":[100,100]},"p":{"a":0,"k":[0,0]},"r":{"a":0,"k":0}}]}],"op":720},{"ty":4,"nm":"Group 4","ip":0,"st":0,"ind":5,"hix":4,"ks":{"o":{"a":1,"k":[{"t":0,"s":[0],"e":[0],"i":{"x":[1],"y":[1]},"o":{"x":[0],"y":[0]}},{"t":239,"s":[0],"e":[100],"i":{"x":[1],"y":[1]},"o":{"x":[0],"y":[0]}},{"t":240,"s":[100],"e":[100],"i":{"x":[1],"y":[1]},"o":{"x":[0],"y":[0]}},{"t":479,"s":[100],"e":[0],"i":{"x":[1],"y":[1]},"o":{"x":[0],"y":[0]}},{"t":480}]},"or":{"a":0,"k":[0,0,0]},"a":{"a":0,"k":[124,88,0]},"p":{"s":true,"x":{"a":0,"k":250},"y":{"a":0,"k":250}},"rx":{"a":0,"k":0},"ry":{"a":0,"k":0},"rz":{"a":0,"k":0},"s":{"a":0,"k":[100,100,100]}},"shapes":[{"ty":"gr","nm":"Group 4 shape group","it":[{"ty":"sh","ks":{"a":0,"k":{"c":false,"v":[[12.5072,98.6643],[100.057,163.493],[235.285,12.5065]],"i":[[0,0],[0,0],[0,0]],"o":[[0,0],[0,0],[0,0]]}}},{"ty":"st","o":{"a":0,"k":100},"c":{"a":0,"k":[0.2784313725490196,0.6392156862745098,0.8549019607843137,1]},"lc":2,"lj":2,"ml":10,"w":{"a":0,"k":25},"d":[{"n":"d","v":{"a":0,"k":320},"nm":"0"},{"n":"g","v":{"a":0,"k":320},"nm":"1"},{"n":"o","v":{"a":1,"k":[{"t":0,"s":[320],"e":[320],"i":{"x":[1],"y":[1]},"o":{"x":[0],"y":[0]}},{"t":240,"s":[320],"e":[0],"i":{"x":[0.515],"y":[0.955]},"o":{"x":[0.455],"y":[0.03]}},{"t":360}]},"nm":"2"}]},{"ty":"fl","o":{"a":0,"k":0},"c":{"a":0,"k":[0,0,0,0]},"r":1},{"ty":"tr","o":{"a":0,"k":100},"a":{"a":0,"k":[0,0]},"s":{"a":0,"k":[100,100]},"p":{"a":0,"k":[0,0]},"r":{"a":0,"k":0}}]}],"op":720},{"ty":4,"nm":"Group 5","ip":0,"st":0,"ind":4,"hix":5,"ks":{"o":{"a":1,"k":[{"t":0,"s":[0],"e":[0],"i":{"x":[1],"y":[1]},"o":{"x":[0],"y":[0]}},{"t":8,"s":[0],"e":[100],"i":{"x":[1],"y":[1]},"o":{"x":[0],"y":[0]}},{"t":9,"s":[100],"e":[100],"i":{"x":[1],"y":[1]},"o":{"x":[0],"y":[0]}},{"t":479,"s":[100],"e":[0],"i":{"x":[1],"y":[1]},"o":{"x":[0],"y":[0]}},{"t":480}]},"or":{"a":0,"k":[0,0,0]},"a":{"a":0,"k":[124,88,0]},"p":{"s":true,"x":{"a":0,"k":250},"y":{"a":0,"k":250}},"rx":{"a":0,"k":0},"ry":{"a":0,"k":0},"rz":{"a":0,"k":0},"s":{"a":0,"k":[100,100,100]}},"shapes":[{"ty":"gr","nm":"Group 5 shape group","it":[{"ty":"sh","ks":{"a":0,"k":{"c":false,"v":[[12.5072,98.6654],[100.057,163.493],[235.285,12.5065]],"i":[[0,0],[0,0],[0,0]],"o":[[0,0],[0,0],[0,0]]}}},{"ty":"st","o":{"a":0,"k":100},"c":{"a":0,"k":[0.9490196078431372,0.8980392156862745,0.17254901960784313,1]},"lc":2,"lj":2,"ml":10,"w":{"a":0,"k":25},"d":[{"n":"d","v":{"a":0,"k":320},"nm":"0"},{"n":"g","v":{"a":0,"k":320},"nm":"1"},{"n":"o","v":{"a":1,"k":[{"t":0,"s":[320],"e":[320],"i":{"x":[1],"y":[1]},"o":{"x":[0],"y":[0]}},{"t":120,"s":[320],"e":[0],"i":{"x":[0.515],"y":[0.955]},"o":{"x":[0.455],"y":[0.03]}},{"t":240}]},"nm":"2"}]},{"ty":"fl","o":{"a":0,"k":0},"c":{"a":0,"k":[0,0,0,0]},"r":1},{"ty":"tr","o":{"a":0,"k":100},"a":{"a":0,"k":[0,0]},"s":{"a":0,"k":[100,100]},"p":{"a":0,"k":[0,0]},"r":{"a":0,"k":0}}]}],"op":720},{"ty":4,"nm":"Group 1","ip":0,"st":0,"ind":3,"hix":6,"ks":{"o":{"a":0,"k":100},"or":{"a":0,"k":[0,0,0]},"a":{"a":0,"k":[124,88,0]},"p":{"s":true,"x":{"a":0,"k":250},"y":{"a":0,"k":250}},"rx":{"a":0,"k":0},"ry":{"a":0,"k":0},"rz":{"a":0,"k":0},"s":{"a":0,"k":[100,100,100]}},"shapes":[{"ty":"gr","nm":"Group 1 shape group","it":[{"ty":"sh","ks":{"a":0,"k":{"c":false,"v":[[12.5071,98.6648],[100.056,163.493],[235.283,12.5064]],"i":[[0,0],[0,0],[0,0]],"o":[[0,0],[0,0],[0,0]]}}},{"ty":"st","o":{"a":0,"k":100},"c":{"a":0,"k":[0.9450980392156862,0.34509803921568627,0.34509803921568627,1]},"lc":2,"lj":2,"ml":10,"w":{"a":0,"k":25},"d":[{"n":"d","v":{"a":0,"k":320},"nm":"0"},{"n":"g","v":{"a":0,"k":320},"nm":"1"},{"n":"o","v":{"a":0,"k":320},"nm":"2"}]},{"ty":"fl","o":{"a":0,"k":0},"c":{"a":0,"k":[0,0,0,0]},"r":1},{"ty":"tr","o":{"a":0,"k":100},"a":{"a":0,"k":[0,0]},"s":{"a":0,"k":[100,100]},"p":{"a":0,"k":[0,0]},"r":{"a":0,"k":0}}]}],"op":720},{"ty":4,"nm":"Group 2","ip":0,"st":0,"ind":2,"hix":2,"ks":{"o":{"a":1,"k":[{"t":0,"s":[100],"e":[100],"i":{"x":[1],"y":[1]},"o":{"x":[0],"y":[0]}},{"t":239,"s":[100],"e":[0],"i":{"x":[1],"y":[1]},"o":{"x":[0],"y":[0]}},{"t":240,"s":[0],"e":[0],"i":{"x":[1],"y":[1]},"o":{"x":[0],"y":[0]}},{"t":479,"s":[0],"e":[100],"i":{"x":[1],"y":[1]},"o":{"x":[0],"y":[0]}},{"t":480}]},"or":{"a":0,"k":[0,0,0]},"a":{"a":0,"k":[124,88,0]},"p":{"s":true,"x":{"a":0,"k":250},"y":{"a":0,"k":250}},"rx":{"a":0,"k":0},"ry":{"a":0,"k":0},"rz":{"a":0,"k":0},"s":{"a":0,"k":[100,100,100]}},"shapes":[{"ty":"gr","nm":"Group 2 shape group","it":[{"ty":"sh","ks":{"a":0,"k":{"c":false,"v":[[12.5072,98.6643],[100.057,163.493],[235.285,12.5065]],"i":[[0,0],[0,0],[0,0]],"o":[[0,0],[0,0],[0,0]]}}},{"ty":"st","o":{"a":0,"k":100},"c":{"a":0,"k":[0.5647058823529412,0.792156862745098,0.43137254901960786,1]},"lc":2,"lj":2,"ml":10,"w":{"a":0,"k":25},"d":[{"n":"d","v":{"a":0,"k":320},"nm":"0"},{"n":"g","v":{"a":0,"k":320},"nm":"1"},{"n":"o","v":{"a":1,"k":[{"t":0,"s":[319.995],"e":[0],"i":{"x":[0.515],"y":[0.955]},"o":{"x":[0.455],"y":[0.03]}},{"t":120,"s":[0],"e":[0],"i":{"x":[1],"y":[1]},"o":{"x":[0],"y":[0]}},{"t":479,"s":[0],"e":[320],"i":{"x":[1],"y":[1]},"o":{"x":[0],"y":[0]}},{"t":480,"s":[320],"e":[0],"i":{"x":[0.515],"y":[0.955]},"o":{"x":[0.455],"y":[0.03]}},{"t":600,"s":[0],"e":[319.995],"i":{"x":[0.515],"y":[0.955]},"o":{"x":[0.455],"y":[0.03]}},{"t":720}]},"nm":"2"}]},{"ty":"fl","o":{"a":0,"k":0},"c":{"a":0,"k":[0,0,0,0]},"r":1},{"ty":"tr","o":{"a":0,"k":100},"a":{"a":0,"k":[0,0]},"s":{"a":0,"k":[100,100]},"p":{"a":0,"k":[0,0]},"r":{"a":0,"k":0}}]}],"op":720},{"ty":4,"nm":"Group 3b","ip":0,"st":0,"ind":1,"hix":1,"ks":{"o":{"a":1,"k":[{"t":0,"s":[0],"e":[0],"i":{"x":[1],"y":[1]},"o":{"x":[0],"y":[0]}},{"t":120,"s":[0],"e":[0],"i":{"x":[1],"y":[1]},"o":{"x":[0],"y":[0]}},{"t":479,"s":[0],"e":[100],"i":{"x":[1],"y":[1]},"o":{"x":[0],"y":[0]}},{"t":480,"s":[100],"e":[100],"i":{"x":[1],"y":[1]},"o":{"x":[0],"y":[0]}},{"t":599,"s":[100],"e":[0],"i":{"x":[1],"y":[1]},"o":{"x":[0],"y":[0]}},{"t":600}]},"or":{"a":0,"k":[0,0,0]},"a":{"a":0,"k":[124,88,0]},"p":{"s":true,"x":{"a":0,"k":250},"y":{"a":0,"k":250}},"rx":{"a":0,"k":0},"ry":{"a":0,"k":0},"rz":{"a":0,"k":0},"s":{"a":0,"k":[100,100,100]}},"shapes":[{"ty":"gr","nm":"Group 3b shape group","it":[{"ty":"sh","ks":{"a":0,"k":{"c":false,"v":[[12.5072,98.6643],[100.057,163.493],[235.285,12.5065]],"i":[[0,0],[0,0],[0,0]],"o":[[0,0],[0,0],[0,0]]}}},{"ty":"st","o":{"a":0,"k":100},"c":{"a":0,"k":[0.9490196078431372,0.5529411764705883,0.20784313725490197,1]},"lc":2,"lj":2,"ml":10,"w":{"a":0,"k":25}},{"ty":"fl","o":{"a":0,"k":0},"c":{"a":0,"k":[0,0,0,0]},"r":1},{"ty":"tr","o":{"a":0,"k":100},"a":{"a":0,"k":[0,0]},"s":{"a":0,"k":[100,100]},"p":{"a":0,"k":[0,0]},"r":{"a":0,"k":0}}]}],"op":720}],"op":720,"w":500,"h":500}